README.rst
setup.py
country_currencies/__init__.py
country_currencies/data.py
country_currencies.egg-info/PKG-INFO
country_currencies.egg-info/SOURCES.txt
country_currencies.egg-info/dependency_links.txt
country_currencies.egg-info/top_level.txt