Metadata-Version: 1.0
Name: country-currencies
Version: 0.2
Summary: mapping of ISO-3166 country codes to their respective currencies
Home-page: UNKNOWN
Author: Wil Tan
Author-email: wil@cloudregistry.net
License: MIT/X
Platform: UNKNOWN
